Workbook

Sheet How To — Step by Step
B2: M&A ACCRETION / DILUTION MODEL — STEP-BY-STEP GUIDE
B3: Microsoft / Activision Blizzard | Deal closed October 13, 2023 | $68.7B all-cash
B6: What is accretion / dilution analysis?
B7: Accretion / dilution measures whether an acquisition INCREASES or DECREASES the acquirer's earnings per share (EPS). If pro forma EPS > standalone EPS, the deal is ACCRETIVE. If pro forma EPS < standalone EPS, it is DILUTIVE. Every IB analyst builds this model for every deal. It is the primary financial health check before a board approves a transaction.
B9: STEP 1: Sources & Uses of Funds
B10: What you do:
B11: Determine how the acquisition is financed — existing cash, new debt, or new equity (stock). For Microsoft/Activision: 100% cash deal. $20B from MSFT's balance sheet + $50.5B in new debt. No new shares issued → share count unchanged → EPS denominator is fixed.
B12: → See tab: '1 - Sources & Uses'
B13: Why it matters:
B14: Why it matters: the financing mix determines the interest cost (Step 4) and whether the share count changes. All-cash deals are simpler — only the numerator (net income) changes.
B16: STEP 2: Standalone Financials
B17: What you do:
... B51: COLOUR CODING LEGEND — used throughout this workbook
B53: Blue text | C53: Hardcoded inputs — numbers you can change for different scenarios
B54: Black text | C54: Formula-calculated outputs — automatically update when inputs change
B55: Green text | C55: Cross-sheet links pulling data from another tab in this workbook
B56: Navy background | C56: Section headers and titles
B57: Light blue background | C57: Key input or output highlighted for emphasis
B58: Light green background | C58: Accretive outcome / positive EPS impact
B59: Light red background | C59: Dilutive outcome / negative EPS impact
B60: Light amber background | C60: Warning / sensitivity / assumption zone

Sheet 1 - Sources & Uses
B2: STEP 1: SOURCES & USES OF FUNDS
B3: How is the $68.7B acquisition financed? | All-cash deal | No new shares issued
B5: Line Item | C5: Amount ($M) | D5: % of Total | E5: Notes / Source
B7: USES OF FUNDS
B8: Acquisition price (equity value) | C8: 68700 | E8: Source: MSFT press release Jan 18 2022. $95.00/share × 723.7M ATVI diluted shares
B9: Transaction fees (advisory, legal, financing) | C9: 800 | E9: Estimated; typical 1.0–1.5% of deal value for complex cross-border transactions
B10: Refinancing of ATVI net debt assumed | C10: 970 | E10: ATVI LTM net debt position at close; must be repaid or refinanced on acquisition
B12: TOTAL USES | C12: =SUM(C8:C10) | D12: =C12/C12
B14: SOURCES OF FUNDS
B15: Cash from MSFT balance sheet | C15: 20000 | E15: MSFT had ~$111B liquid assets; deployed $20B to minimize new debt quantum
B16: New long-term bonds issued (10–30 year) | C16: 35000 | E16: MSFT Aaa/AAA rated — issued at historically tight spreads given credit quality
B17: New medium-term notes (3–5 year) | C17: 10000 | E17: Diversified maturity profile to reduce refinancing risk concentration
B18: Commercial paper / short-term borrowings | C18: 5470 | E18: Bridged until long-term bonds fully placed in market
B20: TOTAL SOURCES | C20: =SUM(C15:C18) | D20: =C20/C20
B22: CHECK: Sources − Uses (should be $0) | C22: =C20-C12 | E22: Must equal zero — if not, check for input errors in Sources or Uses above
B24: FINANCING MIX BREAKDOWN
B25: Cash from balance sheet | C25: =C15 | D25: =C15/C20
B26: Long-term bonds | C26: =C16 | D26: =C16/C20
B27: Medium-term notes | C27: =C17 | D27: =C17/C20
B28: Commercial paper | C28: =C18 | D28: =C18/C20
B30: Key implication: NO new MSFT shares issued | C30: All-cash → share count unchanged → EPS denominator fixed at 7,434M diluted shares throughout model

Sheet 2 - Standalone P&L
B2: STEP 2: STANDALONE INCOME STATEMENTS
B3: Pre-deal income statements | FY2023E at time of close | $M
B5: Line Item | C5: Microsoft (MSFT) | D5: Activision (ATVI) | E5: Notes
B7: Revenue | C7: 211915 | D7: 8803 | E7: MSFT: FY2023 10-K. ATVI: LTM at close per last filed 10-Q
B8: Cost of Revenue | C8: -65863 | D8: -2892 | E8: Direct costs of products/services sold
B9: Gross Profit | C9: =C7+C8 | D9: =D7+D8
B10: Research & Development | C10: -29510 | D10: -1040 | E10: MSFT R&D; ATVI game development costs
B11: Sales, General & Administrative | C11: -24456 | D11: -1101 | E11: Corporate overhead, marketing, admin
B12: Operating Income (EBIT) | C12: =C9+C10+C11 | D12: =D9+D10+D11
B13: Interest Income / (Expense), net | C13: 1413 | D13: 218 | E13: MSFT net interest on $111B liquid assets
B14: Other Income / (Expense) | C14: -78 | D14: -35 | E14: FX, equity method investments
B15: Pre-Tax Income (EBT) | C15: =C12+C13+C14 | D15: =D12+D13+D14
B16: Income Tax Expense | C16: -16950 | D16: -381 | E16: MSFT effective rate 18.8%; ATVI ~20.0%
B17: Net Income | C17: =C15+C16 | D17: =D15+D16
B19: Diluted Shares Outstanding (M) | C19: 7434 | D19: 724 | E19: MSFT: 10-K. ATVI: pre-deal shares before cash settlement
B20: Diluted EPS ($) | C20: =C17/C19 | D20: =D17/D19
B21: Effective Tax Rate | C21: =ABS(C16)/C15 | D21: =ABS(D16)/D15
B23: P/E Multiple (at deal price / current price) | C23: 409 | D23: 95
B24: EBITDA | C24: 105672 | D24: 1820 | E24: EBITDA = EBIT + D&A; used for EV/EBITDA valuation multiple
B25: EV/EBITDA (at deal price / market cap) | C25: 2452000 | D25: 68700 | E25: MSFT: market cap at deal announcement. ATVI: deal enterprise value paid
B26: EV/EBITDA multiple | C26: =C25/C24 | D26: =D25/D24 | E26: MSFT trades at ~23x EBITDA; ATVI acquired at ~37.7x — significant premium paid
B28: KEY: MSFT standalone EPS (from row 20) is the BASELINE — every pro forma calculation compares against this number.

Sheet 3 - PPA & Amortisation
B2: STEP 3: PURCHASE PRICE ALLOCATION (PPA) & AMORTISATION
B3: Intangible asset step-up and annual amortisation schedule | $M
B5: Intangible Asset | C5: Fair Value ($M) | D5: Useful Life (yrs) | E5: Annual Amort. | F5: Tax Deductible? | G5: After-Tax Amort. | H5: Notes
B7: IDENTIFIABLE INTANGIBLE ASSETS ACQUIRED
B8: Developed game titles (CoD, WoW, Overwatch, etc.) | C8: 8500 | D8: 6 | E8: =IF(D8>0,C8/D8,0) | F8: Yes | G8: =IF(F8="Yes",E8*(1-'4 - Financing Cost'!$C$12),E8) | H8: Core IP; amortised over estimated economic life of franchise
B9: Customer relationships / active player base | C9: 3200 | D9: 10 | E9: =IF(D9>0,C9/D9,0) | F9: Yes | G9: =IF(F9="Yes",E9*(1-'4 - Financing Cost'!$C$12),E9) | H9: 300M+ monthly active users; relationship value amortised over retention curve
B10: In-process R&D (game pipeline) | C10: 1400 | D10: 0 | E10: 0 | F10: No | G10: 0 | H10: Expensed immediately at acquisition close per ASC 805; no ongoing amortisation
B11: Technology platform / engine | C11: 1100 | D11: 5 | E11: =IF(D11>0,C11/D11,0) | F11: Yes | G11: =IF(F11="Yes",E11*(1-'4 - Financing Cost'!$C$12),E11) | H11: Proprietary game development tools and engine technology
B12: Trade names and brand (Blizzard, King, Activision) | C12: 1800 | D12: 0 | E12: 0 | F12: No | G12: 0 | H12: Indefinite-life intangible — NOT amortised, tested annually for impairment
B14: Goodwill (residual premium) | C14: ='1 - Sources & Uses'!C8-SUM(C8:C12)-8470 | D14: N/A | E14: - | F14: No | G14: - | H14: Residual = Total deal cost ($70,470M) − Identified intangibles ($16,000M) − ATVI net tangible book value ($8,470M at close). NOT amortised; impairment tested annually (ASC 350)
B16: Total Identified Intangibles + Goodwill | C16: =C14+SUM(C8:C12)
B18: ANNUAL AMORTISATION SCHEDULE (Years 1–10)
B19: Asset | C19: Yr 1 | D19: Yr 2 | E19: Yr 3 | F19: Yr 4 | G19: Yr 5 | H19: Yr 6–10
B20: Developed game titles (CoD, WoW, Overwatch, e | C20: =C8/D8 | D20: =C8/D8 | E20: =C8/D8 | F20: =C8/D8 | G20: =C8/D8 | H20: =C8/D8
B21: Customer relationships / active player base | C21: =C9/D9 | D21: =C9/D9 | E21: =C9/D9 | F21: =C9/D9 | G21: =C9/D9 | H21: =C9/D9
B22: In-process R&D (game pipeline) | C22: 0 | D22: 0 | E22: 0 | F22: 0 | G22: 0 | H22: 0
B23: Technology platform / engine | C23: =C11/D11 | D23: =C11/D11 | E23: =C11/D11 | F23: =C11/D11 | G23: =C11/D11 | H23: 0
B24: Trade names and brand (Blizzard, King, Activi | C24: 0 | D24: 0 | E24: 0 | F24: 0 | G24: 0 | H24: 0
B26: Total Annual Amortisation (GAAP charge) | C26: =SUM(C20:C24) | D26: =SUM(D20:D24) | E26: =SUM(E20:E24) | F26: =SUM(F20:F24) | G26: =SUM(G20:G24) | H26: =SUM(H20:H24)
B28: EPS IMPACT OF AMORTISATION (key model output)
B29: Annual GAAP amortisation charge ($M) | C29: =C26 | H29: Links to Pro Forma EPS model
B30: Tax rate (from Financing tab) | C30: ='4 - Financing Cost'!$C$12
B31: After-tax amortisation ($M) | C31: =C29*(1-C30)
B32: EPS drag from amortisation ($/share) | C32: =-C31/'2 - Standalone P&L'!C19 | H32: After-tax amort divided by MSFT diluted shares. Negative = EPS drag. Approx -0.17 per year at base case

Sheet 4 - Financing Cost
B2: STEP 4: FINANCING COST — INTEREST EXPENSE ON NEW DEBT
B3: Annual interest cost of the $50.5B new debt raised to fund the acquisition | $M
B5: Item | C5: Amount / Rate | D5: Annual Cost ($M) | E5: Notes
B7: KEY ASSUMPTIONS
B8: Total new debt raised ($M) | C8: 50470 | E8: Total new debt = Long-term bonds + MTNs + Commercial paper from Sources and Uses tab
B9: Cash deployed from balance sheet ($M) | C9: 20000 | E9: Opportunity cost: cash was earning ~4.5% before being deployed
B10: Blended interest rate on new debt | C10: 0.046 | E10: MSFT Aaa/AAA rated. LT bonds ~4.75%, MTNs ~4.25%, CP ~5.2% — blended ~4.6%
B11: Foregone yield on cash deployed | C11: 0.045 | E11: Prior yield on MSFT liquid asset portfolio (~4.5% short-dated Treasuries)
B12: Blended tax rate (MSFT effective rate) | C12: 0.188 | E12: MSFT FY2023 effective tax rate 18.8%. Source: MSFT 10-K FY2023 Note 13
B14: ANNUAL INTEREST COST BREAKDOWN
B15: Interest on new long-term bonds ($M) | C15: ='1 - Sources & Uses'!C16 | D15: =C15*C10 | E15: 35,000 × 4.75% blended (actual rate varies by tranche)
B16: Interest on medium-term notes ($M) | C16: ='1 - Sources & Uses'!C17 | D16: =C16*C10
B17: Interest on commercial paper ($M) | C17: ='1 - Sources & Uses'!C18 | D17: =C17*C10
B18: Foregone interest income on cash deployed ($M) | C18: =C9 | D18: =C9*C11 | E18: Opportunity cost of using balance sheet cash. Often excluded by bulls; should be included for conservatism
B20: TOTAL GROSS FINANCING COST ($M) | D20: =SUM(D15:D18)
B21: Less: tax shield on interest (deductible expense) | D21: =-D20*C12 | E21: Interest expense is tax-deductible — reduces taxable income and therefore tax paid
B23: AFTER-TAX FINANCING COST ($M) | D23: =D20*(1-C12)
B25: EPS IMPACT
B26: After-tax financing cost ($M) | D26: =D23
B27: MSFT diluted shares (M) | D27: ='2 - Standalone P&L'!C19
B28: EPS drag from financing ($/share) | D28: =-D23/D27 | E28: Negative = EPS drag. Formula: −After-tax cost ÷ Diluted shares ÷ 1000 (M to units)
B30: INTERVIEW INSIGHT: Why is interest tax-deductible? Because under GAAP and tax law, interest paid on debt reduces taxable income. The government effectively subsidises 18.8¢ of every dollar of interest Microsoft pays. This is the 'debt tax shield' — a core concept in capital structure theory (Modigliani-Miller).

Sheet 5 - Synergies
B2: STEP 5: SYNERGY ASSUMPTIONS & REALISATION SCHEDULE
B3: Annual run-rate synergies and year-by-year realisation | $M | 3-year ramp
B5: Synergy Item | C5: Type | D5: Run-Rate ($M) | E5: Source / Rationale | F5: Confidence
B7: COST SYNERGIES — higher confidence, typically modelled at full credit
B8: Corporate function overlap (Finance, HR, Legal, IT) | C8: Cost | D8: 450 | E8: ~3,750 roles eliminated × $120K avg total comp | F8: High
B9: Infrastructure / cloud migration to Azure | C9: Cost | D9: 380 | E9: ATVI workloads move to MSFT Azure from AWS/GCP | F9: High
B10: Procurement savings (shared vendor contracts) | C10: Cost | D10: 180 | E10: Leverage MSFT's $50B+ annual procurement scale | F10: Medium
B11: Real estate consolidation | C11: Cost | D11: 90 | E11: ATVI offices overlap with MSFT in LA, Seattle, Dublin | F11: Medium
B12: Total Cost Synergies | D12: =SUM(D8:D11)
B14: REVENUE SYNERGIES — lower confidence; apply 50% haircut in conservative case
B15: Game Pass subscriber uplift from ATVI titles | C15: Revenue | D15: 800 | E15: CoD/WoW/Overwatch on Game Pass drives net adds at $15/mo | F15: Medium
B16: Mobile gaming monetisation (King + MSFT distribution) | C16: Revenue | D16: 600 | E16: Candy Crush + MSFT mobile reach + Azure backend savings | F16: Low
B17: Cross-sell / upsell between player bases | C17: Revenue | D17: 350 | E17: ATVI players upgrade to Xbox/MSFT ecosystem products | F17: Low
B18: International market expansion (China, EM) | C18: Revenue | D18: 250 | E18: ATVI titles + MSFT enterprise relationships open new markets | F18: Low
B19: Total Revenue Synergies (gross) | D19: =SUM(D15:D18)
B21: TOTAL SYNERGIES SUMMARY
B22: Total Cost Synergies | D22: =D12
B23: Total Revenue Synergies (gross) | D23: =D19
B24: Revenue synergy haircut (conservative case) | C24: 0.5 | E24: Standard practice: discount revenue synergies 50% to reflect execution risk vs. cost synergies
B25: Adjusted Revenue Synergies (post-haircut) | D25: =D23*(1-C24)
B26: TOTAL RUN-RATE SYNERGIES (base case) | D26: =D22+D25
B28: REALISATION SCHEDULE (how quickly synergies are achieved)
B29: Item | C29: Run-Rate | D29: Year 1 | E29: Year 2 | F29: Year 3
B30: Realisation rate assumption | D30: 0.4 | E30: 0.7 | F30: 1
B31: Cost synergies achieved ($M) | C31: =D12 | D31: =C31*D30 | E31: =C31*E30 | F31: =C31*F30
B32: Revenue synergies achieved ($M) | C32: =D25 | D32: =C32*D30 | E32: =C32*E30 | F32: =C32*F30
B33: Total gross synergies realised ($M) | C33: =D26 | D33: =D31+D32 | E33: =E31+E32 | F33: =F31+F32
B34: Tax rate | C34: ='4 - Financing Cost'!$C$12
B35: After-tax synergies ($M) — flows to pro forma NI | D35: =D33*(1-C34) | E35: =E33*(1-C34) | F35: =F33*(1-C34)
B36: EPS uplift from synergies ($/share) | D36: =D35/'2 - Standalone P&L'!C19 | E36: =E35/'2 - Standalone P&L'!C19 | F36: =F35/'2 - Standalone P&L'!C19

Sheet 6 - Pro Forma EPS
B2: STEP 6: PRO FORMA EPS & ACCRETION / DILUTION VERDICT
B3: Combines all prior steps into the final answer | $M unless noted
B5: Line Item | C5: Year 1 | D5: Year 2 | E5: Year 3 | F5: Run-Rate | G5: Formula / Notes
B7: PRO FORMA NET INCOME BUILD
B8: MSFT standalone net income ($M) | C8: ='2 - Standalone P&L'!C17 | D8: ='2 - Standalone P&L'!C17 | E8: ='2 - Standalone P&L'!C17 | F8: ='2 - Standalone P&L'!C17 | G8: Links from Standalone P&L tab. Fixed across all years (no growth modelled here)
B9: (+) ATVI acquired net income ($M) | C9: ='2 - Standalone P&L'!D17 | D9: ='2 - Standalone P&L'!D17 | E9: ='2 - Standalone P&L'!D17 | F9: ='2 - Standalone P&L'!D17 | G9: ATVI net income added to combined entity. Assume flat for simplicity; can add growth
B10: (−) After-tax financing cost ($M) | C10: =-'4 - Financing Cost'!D23 | D10: =-'4 - Financing Cost'!D23 | E10: =-'4 - Financing Cost'!D23 | F10: =-'4 - Financing Cost'!D23 | G10: Annual interest cost after tax shield. Fixed; reduces as debt is optionally repaid
B11: (−) After-tax PPA amortisation ($M) | C11: =-'3 - PPA & Amortisation'!C31 | D11: =-'3 - PPA & Amortisation'!C31 | E11: =-'3 - PPA & Amortisation'!C31 | F11: =-'3 - PPA & Amortisation'!C31 | G11: Declines over time as assets become fully amortised. Run-rate column shows steady-state
B12: (+) After-tax synergies — realised ($M) | C12: ='5 - Synergies'!D35 | D12: ='5 - Synergies'!E35 | E12: ='5 - Synergies'!F35 | F12: ='5 - Synergies'!D26*(1-'4 - Financing Cost'!$C$12) | G12: Ramps up: 40% Yr1 → 70% Yr2 → 100% Yr3 → full run-rate thereafter
B14: PRO FORMA NET INCOME ($M) | C14: =C8+C9+C10+C11+C12 | D14: =D8+D9+D10+D11+D12 | E14: =E8+E9+E10+E11+E12 | F14: =F8+F9+F10+F11+F12
B16: PRO FORMA EPS — THE VERDICT
B17: Diluted shares outstanding (M) — unchanged (all-cash) | C17: ='2 - Standalone P&L'!C19 | D17: ='2 - Standalone P&L'!C19 | E17: ='2 - Standalone P&L'!C19 | F17: ='2 - Standalone P&L'!C19
B18: PRO FORMA EPS ($/share) | C18: =C14/C17 | D18: =D14/D17 | E18: =E14/E17 | F18: =F14/F17
B19: MSFT standalone EPS ($/share) | C19: ='2 - Standalone P&L'!C20 | D19: ='2 - Standalone P&L'!C20 | E19: ='2 - Standalone P&L'!C20 | F19: ='2 - Standalone P&L'!C20
B20: Accretion / (Dilution) ($) per share | C20: =C18-C19 | D20: =D18-D19 | E20: =E18-E19 | F20: =F18-F19
B21: ACCRETION / (DILUTION) % vs. standalone | C21: =C20/C19 | D21: =D20/D19 | E21: =E20/E19 | F21: =F20/F19
B23: SENSITIVITY TABLE: Year 1 EPS Accretion / (Dilution) %
B24: Rows = blended interest rate on new debt | Columns = Year 1 gross synergies realised ($M)
B25: Rate \ Synergies → | C25: $0M | D25: $500M | E25: $1,000M | F25: $1,500M | G25: $2,000M | H25: $2,500M | I25: $3,500M
B26: 3.0% | C26: =( ('2 - Standalone P&L'!C17+'2 - Standalone P&L'!D17-('4 - Financing Cost'!C8*0.03+'4 - Financing Cost'!C9*'4 - Financing Cost'!C11)*(1-'4 - Financing Cost'!C12)-'3 - PPA & Amortisation'!C31+0*(1-'4 - Financing Cost'!C12))/'2 - Standalone P&L'!C19-'2 - Standalone P&L'!C20)/'2 - Standalone P&L'!C20 | D26: =( ('2 - Standalone P&L'!C17+'2 - Standalone P&L'!D17-('4 - Financing Cost'!C8*0.03+'4 - Financing Cost'!C9*'4 - Financing Cost'!C11)*(1-'4 - Financing Cost'!C12)-'3 - PPA & Amortisation'!C31+500*(1-'4 - Financing Cost'!C12))/'2 - Standalone P&L'!C19-'2 - Standalone P&L'!C20)/'2 - Standalone P&L'!C20 | E26: =( ('2 - Standalone P&L'!C17+'2 - Standalone P&L'!D17-('4 - Financing Cost'!C8*0.03+'4 - Financing Cost'!C9*'4 - Financing Cost'!C11)*(1-'4 - Financing Cost'!C12)-'3 - PPA & Amortisation'!C31+1000*(1-'4 - Financing Cost'!C12))/'2 - Standalone P&L'!C19-'2 - Standalone P&L'!C20)/'2 - Standalone P&L'!C20 | F26: =( ('2 - Standalone P&L'!C17+'2 - Standalone P&L'!D17-('4 - Financing Cost'!C8*0.03+'4 - Financing Cost'!C9*'4 - Financing Cost'!C11)*(1-'4 - Financing Cost'!C12)-'3 - PPA & Amortisation'!C31+1500*(1-'4 - Financing Cost'!C12))/'2 - Standalone P&L'!C19-'2 - Standalone P&L'!C20)/'2 - Standalone P&L'!C20 | G26: =( ('2 - Standalone P&L'!C17+'2 - Standalone P&L'!D17-('4 - Financing Cost'!C8*0.03+'4 - Financing Cost'!C9*'4 - Financing Cost'!C11)*(1-'4 - Financing Cost'!C12)-'3 - PPA & Amortisation'!C31+2000*(1-'4 - Financing Cost'!C12))/'2 - Standalone P&L'!C19-'2 - Standalone P&L'!C20)/'2 - Standalone P&L'!C20 | H26: =( ('2 - Standalone P&L'!C17+'2 - Standalone P&L'!D17-('4 - Financing Cost'!C8*0.03+'4 - Financing Cost'!C9*'4 - Financing Cost'!C11)*(1-'4 - Financing Cost'!C12)-'3 - PPA & Amortisation'!C31+2500*(1-'4 - Financing Cost'!C12))/'2 - Standalone P&L'!C19-'2 - Standalone P&L'!C20)/'2 - Standalone P&L'!C20 | I26: =( ('2 - Standalone P&L'!C17+'2 - Standalone P&L'!D17-('4 - Financing Cost'!C8*0.03+'4 - Financing Cost'!C9*'4 - Financing Cost'!C11)*(1-'4 - Financing Cost'!C12)-'3 - PPA & Amortisation'!C31+3500*(1-'4 - Financing Cost'!C12))/'2 - Standalone P&L'!C19-'2 - Standalone P&L'!C20)/'2 - Standalone P&L'!C20
B27: 4.0% | C27: =( ('2 - Standalone P&L'!C17+'2 - Standalone P&L'!D17-('4 - Financing Cost'!C8*0.04+'4 - Financing Cost'!C9*'4 - Financing Cost'!C11)*(1-'4 - Financing Cost'!C12)-'3 - PPA & Amortisation'!C31+0*(1-'4 - Financing Cost'!C12))/'2 - Standalone P&L'!C19-'2 - Standalone P&L'!C20)/'2 - Standalone P&L'!C20 | D27: =( ('2 - Standalone P&L'!C17+'2 - Standalone P&L'!D17-('4 - Financing Cost'!C8*0.04+'4 - Financing Cost'!C9*'4 - Financing Cost'!C11)*(1-'4 - Financing Cost'!C12)-'3 - PPA & Amortisation'!C31+500*(1-'4 - Financing Cost'!C12))/'2 - Standalone P&L'!C19-'2 - Standalone P&L'!C20)/'2 - Standalone P&L'!C20 | E27: =( ('2 - Standalone P&L'!C17+'2 - Standalone P&L'!D17-('4 - Financing Cost'!C8*0.04+'4 - Financing Cost'!C9*'4 - Financing Cost'!C11)*(1-'4 - Financing Cost'!C12)-'3 - PPA & Amortisation'!C31+1000*(1-'4 - Financing Cost'!C12))/'2 - Standalone P&L'!C19-'2 - Standalone P&L'!C20)/'2 - Standalone P&L'!C20 | F27: =( ('2 - Standalone P&L'!C17+'2 - Standalone P&L'!D17-('4 - Financing Cost'!C8*0.04+'4 - Financing Cost'!C9*'4 - Financing Cost'!C11)*(1-'4 - Financing Cost'!C12)-'3 - PPA & Amortisation'!C31+1500*(1-'4 - Financing Cost'!C12))/'2 - Standalone P&L'!C19-'2 - Standalone P&L'!C20)/'2 - Standalone P&L'!C20 | G27: =( ('2 - Standalone P&L'!C17+'2 - Standalone P&L'!D17-('4 - Financing Cost'!C8*0.04+'4 - Financing Cost'!C9*'4 - Financing Cost'!C11)*(1-'4 - Financing Cost'!C12)-'3 - PPA & Amortisation'!C31+2000*(1-'4 - Financing Cost'!C12))/'2 - Standalone P&L'!C19-'2 - Standalone P&L'!C20)/'2 - Standalone P&L'!C20 | H27: =( ('2 - Standalone P&L'!C17+'2 - Standalone P&L'!D17-('4 - Financing Cost'!C8*0.04+'4 - Financing Cost'!C9*'4 - Financing Cost'!C11)*(1-'4 - Financing Cost'!C12)-'3 - PPA & Amortisation'!C31+2500*(1-'4 - Financing Cost'!C12))/'2 - Standalone P&L'!C19-'2 - Standalone P&L'!C20)/'2 - Standalone P&L'!C20 | I27: =( ('2 - Standalone P&L'!C17+'2 - Standalone P&L'!D17-('4 - Financing Cost'!C8*0.04+'4 - Financing Cost'!C9*'4 - Financing Cost'!C11)*(1-'4 - Financing Cost'!C12)-'3 - PPA & Amortisation'!C31+3500*(1-'4 - Financing Cost'!C12))/'2 - Standalone P&L'!C19-'2 - Standalone P&L'!C20)/'2 - Standalone P&L'!C20
B28: 4.6% | C28: =( ('2 - Standalone P&L'!C17+'2 - Standalone P&L'!D17-('4 - Financing Cost'!C8*0.046+'4 - Financing Cost'!C9*'4 - Financing Cost'!C11)*(1-'4 - Financing Cost'!C12)-'3 - PPA & Amortisation'!C31+0*(1-'4 - Financing Cost'!C12))/'2 - Standalone P&L'!C19-'2 - Standalone P&L'!C20)/'2 - Standalone P&L'!C20 | D28: =( ('2 - Standalone P&L'!C17+'2 - Standalone P&L'!D17-('4 - Financing Cost'!C8*0.046+'4 - Financing Cost'!C9*'4 - Financing Cost'!C11)*(1-'4 - Financing Cost'!C12)-'3 - PPA & Amortisation'!C31+500*(1-'4 - Financing Cost'!C12))/'2 - Standalone P&L'!C19-'2 - Standalone P&L'!C20)/'2 - Standalone P&L'!C20 | E28: =( ('2 - Standalone P&L'!C17+'2 - Standalone P&L'!D17-('4 - Financing Cost'!C8*0.046+'4 - Financing Cost'!C9*'4 - Financing Cost'!C11)*(1-'4 - Financing Cost'!C12)-'3 - PPA & Amortisation'!C31+1000*(1-'4 - Financing Cost'!C12))/'2 - Standalone P&L'!C19-'2 - Standalone P&L'!C20)/'2 - Standalone P&L'!C20 | F28: =( ('2 - Standalone P&L'!C17+'2 - Standalone P&L'!D17-('4 - Financing Cost'!C8*0.046+'4 - Financing Cost'!C9*'4 - Financing Cost'!C11)*(1-'4 - Financing Cost'!C12)-'3 - PPA & Amortisation'!C31+1500*(1-'4 - Financing Cost'!C12))/'2 - Standalone P&L'!C19-'2 - Standalone P&L'!C20)/'2 - Standalone P&L'!C20 | G28: =( ('2 - Standalone P&L'!C17+'2 - Standalone P&L'!D17-('4 - Financing Cost'!C8*0.046+'4 - Financing Cost'!C9*'4 - Financing Cost'!C11)*(1-'4 - Financing Cost'!C12)-'3 - PPA & Amortisation'!C31+2000*(1-'4 - Financing Cost'!C12))/'2 - Standalone P&L'!C19-'2 - Standalone P&L'!C20)/'2 - Standalone P&L'!C20 | H28: =( ('2 - Standalone P&L'!C17+'2 - Standalone P&L'!D17-('4 - Financing Cost'!C8*0.046+'4 - Financing Cost'!C9*'4 - Financing Cost'!C11)*(1-'4 - Financing Cost'!C12)-'3 - PPA & Amortisation'!C31+2500*(1-'4 - Financing Cost'!C12))/'2 - Standalone P&L'!C19-'2 - Standalone P&L'!C20)/'2 - Standalone P&L'!C20 | I28: =( ('2 - Standalone P&L'!C17+'2 - Standalone P&L'!D17-('4 - Financing Cost'!C8*0.046+'4 - Financing Cost'!C9*'4 - Financing Cost'!C11)*(1-'4 - Financing Cost'!C12)-'3 - PPA & Amortisation'!C31+3500*(1-'4 - Financing Cost'!C12))/'2 - Standalone P&L'!C19-'2 - Standalone P&L'!C20)/'2 - Standalone P&L'!C20
B29: 5.5% | C29: =( ('2 - Standalone P&L'!C17+'2 - Standalone P&L'!D17-('4 - Financing Cost'!C8*0.055+'4 - Financing Cost'!C9*'4 - Financing Cost'!C11)*(1-'4 - Financing Cost'!C12)-'3 - PPA & Amortisation'!C31+0*(1-'4 - Financing Cost'!C12))/'2 - Standalone P&L'!C19-'2 - Standalone P&L'!C20)/'2 - Standalone P&L'!C20 | D29: =( ('2 - Standalone P&L'!C17+'2 - Standalone P&L'!D17-('4 - Financing Cost'!C8*0.055+'4 - Financing Cost'!C9*'4 - Financing Cost'!C11)*(1-'4 - Financing Cost'!C12)-'3 - PPA & Amortisation'!C31+500*(1-'4 - Financing Cost'!C12))/'2 - Standalone P&L'!C19-'2 - Standalone P&L'!C20)/'2 - Standalone P&L'!C20 | E29: =( ('2 - Standalone P&L'!C17+'2 - Standalone P&L'!D17-('4 - Financing Cost'!C8*0.055+'4 - Financing Cost'!C9*'4 - Financing Cost'!C11)*(1-'4 - Financing Cost'!C12)-'3 - PPA & Amortisation'!C31+1000*(1-'4 - Financing Cost'!C12))/'2 - Standalone P&L'!C19-'2 - Standalone P&L'!C20)/'2 - Standalone P&L'!C20 | F29: =( ('2 - Standalone P&L'!C17+'2 - Standalone P&L'!D17-('4 - Financing Cost'!C8*0.055+'4 - Financing Cost'!C9*'4 - Financing Cost'!C11)*(1-'4 - Financing Cost'!C12)-'3 - PPA & Amortisation'!C31+1500*(1-'4 - Financing Cost'!C12))/'2 - Standalone P&L'!C19-'2 - Standalone P&L'!C20)/'2 - Standalone P&L'!C20 | G29: =( ('2 - Standalone P&L'!C17+'2 - Standalone P&L'!D17-('4 - Financing Cost'!C8*0.055+'4 - Financing Cost'!C9*'4 - Financing Cost'!C11)*(1-'4 - Financing Cost'!C12)-'3 - PPA & Amortisation'!C31+2000*(1-'4 - Financing Cost'!C12))/'2 - Standalone P&L'!C19-'2 - Standalone P&L'!C20)/'2 - Standalone P&L'!C20 | H29: =( ('2 - Standalone P&L'!C17+'2 - Standalone P&L'!D17-('4 - Financing Cost'!C8*0.055+'4 - Financing Cost'!C9*'4 - Financing Cost'!C11)*(1-'4 - Financing Cost'!C12)-'3 - PPA & Amortisation'!C31+2500*(1-'4 - Financing Cost'!C12))/'2 - Standalone P&L'!C19-'2 - Standalone P&L'!C20)/'2 - Standalone P&L'!C20 | I29: =( ('2 - Standalone P&L'!C17+'2 - Standalone P&L'!D17-('4 - Financing Cost'!C8*0.055+'4 - Financing Cost'!C9*'4 - Financing Cost'!C11)*(1-'4 - Financing Cost'!C12)-'3 - PPA & Amortisation'!C31+3500*(1-'4 - Financing Cost'!C12))/'2 - Standalone P&L'!C19-'2 - Standalone P&L'!C20)/'2 - Standalone P&L'!C20
B30: 6.5% | C30: =( ('2 - Standalone P&L'!C17+'2 - Standalone P&L'!D17-('4 - Financing Cost'!C8*0.065+'4 - Financing Cost'!C9*'4 - Financing Cost'!C11)*(1-'4 - Financing Cost'!C12)-'3 - PPA & Amortisation'!C31+0*(1-'4 - Financing Cost'!C12))/'2 - Standalone P&L'!C19-'2 - Standalone P&L'!C20)/'2 - Standalone P&L'!C20 | D30: =( ('2 - Standalone P&L'!C17+'2 - Standalone P&L'!D17-('4 - Financing Cost'!C8*0.065+'4 - Financing Cost'!C9*'4 - Financing Cost'!C11)*(1-'4 - Financing Cost'!C12)-'3 - PPA & Amortisation'!C31+500*(1-'4 - Financing Cost'!C12))/'2 - Standalone P&L'!C19-'2 - Standalone P&L'!C20)/'2 - Standalone P&L'!C20 | E30: =( ('2 - Standalone P&L'!C17+'2 - Standalone P&L'!D17-('4 - Financing Cost'!C8*0.065+'4 - Financing Cost'!C9*'4 - Financing Cost'!C11)*(1-'4 - Financing Cost'!C12)-'3 - PPA & Amortisation'!C31+1000*(1-'4 - Financing Cost'!C12))/'2 - Standalone P&L'!C19-'2 - Standalone P&L'!C20)/'2 - Standalone P&L'!C20 | F30: =( ('2 - Standalone P&L'!C17+'2 - Standalone P&L'!D17-('4 - Financing Cost'!C8*0.065+'4 - Financing Cost'!C9*'4 - Financing Cost'!C11)*(1-'4 - Financing Cost'!C12)-'3 - PPA & Amortisation'!C31+1500*(1-'4 - Financing Cost'!C12))/'2 - Standalone P&L'!C19-'2 - Standalone P&L'!C20)/'2 - Standalone P&L'!C20 | G30: =( ('2 - Standalone P&L'!C17+'2 - Standalone P&L'!D17-('4 - Financing Cost'!C8*0.065+'4 - Financing Cost'!C9*'4 - Financing Cost'!C11)*(1-'4 - Financing Cost'!C12)-'3 - PPA & Amortisation'!C31+2000*(1-'4 - Financing Cost'!C12))/'2 - Standalone P&L'!C19-'2 - Standalone P&L'!C20)/'2 - Standalone P&L'!C20 | H30: =( ('2 - Standalone P&L'!C17+'2 - Standalone P&L'!D17-('4 - Financing Cost'!C8*0.065+'4 - Financing Cost'!C9*'4 - Financing Cost'!C11)*(1-'4 - Financing Cost'!C12)-'3 - PPA & Amortisation'!C31+2500*(1-'4 - Financing Cost'!C12))/'2 - Standalone P&L'!C19-'2 - Standalone P&L'!C20)/'2 - Standalone P&L'!C20 | I30: =( ('2 - Standalone P&L'!C17+'2 - Standalone P&L'!D17-('4 - Financing Cost'!C8*0.065+'4 - Financing Cost'!C9*'4 - Financing Cost'!C11)*(1-'4 - Financing Cost'!C12)-'3 - PPA & Amortisation'!C31+3500*(1-'4 - Financing Cost'!C12))/'2 - Standalone P&L'!C19-'2 - Standalone P&L'!C20)/'2 - Standalone P&L'!C20
B32: Navy cell = base case. Positive % = accretive. Negative % = dilutive. Sensitivity shows how dependent the verdict is on synergy realisation — the most defensible assumption to challenge in an interview.
B34: EPS BRIDGE (Year 1) — sources of accretion / dilution
B36: MSFT standalone EPS | C36: ='2 - Standalone P&L'!C20
B37: (+) ATVI earnings contribution | C37: ='2 - Standalone P&L'!D17/'2 - Standalone P&L'!C19
B38: (−) After-tax interest expense per share | C38: =-'4 - Financing Cost'!D23/'2 - Standalone P&L'!C19
B39: (−) After-tax PPA amortisation per share | C39: =-'3 - PPA & Amortisation'!C31/'2 - Standalone P&L'!C19
B40: (+) After-tax Yr1 synergies per share | C40: ='5 - Synergies'!D35/'2 - Standalone P&L'!C19
B41: = PRO FORMA EPS | C41: =C18
